{
  "$schema": "https://ui.shadcn.com/schema/registry-item.json",
  "name": "src/components/SparkChart/sparkchart.spec",
  "type": "registry:file",
  "dependencies": [
    "@playwright/test"
  ],
  "files": [
    {
      "type": "registry:file",
      "target": "src/components/SparkChart/sparkchart.spec.ts",
      "content": "import { expect, test } from \"@playwright/test\"\n\ntest.describe(\"Expect default spark area chart\", () => {\n  test(\"to be rendered\", async ({ page }) => {\n    await page.goto(\n      \"http://localhost:6006/?path=/story/visualization-sparkareachart--default\",\n    )\n    await expect(\n      page\n        .frameLocator('iframe[title=\"storybook-preview-iframe\"]')\n        .getByTestId(\"spark-area-chart\"),\n    ).toBeVisible()\n  })\n\n  test(\"to render two lines\", async ({ page }) => {\n    await page.goto(\n      \"http://localhost:6006/?path=/story/visualization-sparkareachart--default\",\n    )\n    await expect(\n      page\n        .frameLocator('iframe[title=\"storybook-preview-iframe\"]')\n        .locator('path.recharts-curve.recharts-area-curve[name=\"SolarCells\"]'),\n    ).toBeVisible()\n    await expect(\n      page\n        .frameLocator('iframe[title=\"storybook-preview-iframe\"]')\n        .locator('path.recharts-curve.recharts-area-curve[name=\"Glass\"]'),\n    ).toBeVisible()\n  })\n})\n\ntest.describe(\"Expect default spark bar chart\", () => {\n  test(\"to be rendered\", async ({ page }) => {\n    await page.goto(\n      \"http://localhost:6006/?path=/story/visualization-sparkbarchart--default\",\n    )\n    await expect(\n      page\n        .frameLocator('iframe[title=\"storybook-preview-iframe\"]')\n        .getByTestId(\"spark-bar-chart\"),\n    ).toBeVisible()\n  })\n\n  test(\"to render first two bars\", async ({ page }) => {\n    await page.goto(\n      \"http://localhost:6006/?path=/story/visualization-sparkbarchart--default\",\n    )\n    await expect(\n      page\n        .frameLocator('iframe[title=\"storybook-preview-iframe\"]')\n        .locator(\".recharts-rectangle\")\n        .first(),\n    ).toBeVisible()\n    await expect(\n      page\n        .frameLocator('iframe[title=\"storybook-preview-iframe\"]')\n        .locator(\".recharts-rectangle\")\n        .nth(2),\n    ).toBeVisible()\n  })\n})\n\ntest.describe(\"Expect default spark line chart\", () => {\n  test(\"to be rendered\", async ({ page }) => {\n    await page.goto(\n      \"http://localhost:6006/?path=/story/visualization-sparklinechart--default\",\n    )\n    await expect(\n      page\n        .frameLocator('iframe[title=\"storybook-preview-iframe\"]')\n        .getByTestId(\"spark-line-chart\"),\n    ).toBeVisible()\n  })\n\n  test(\"to render two lines\", async ({ page }) => {\n    await page.goto(\n      \"http://localhost:6006/?path=/story/visualization-sparklinechart--default\",\n    )\n    await expect(\n      page\n        .frameLocator('iframe[title=\"storybook-preview-iframe\"]')\n        .locator('path.recharts-curve.recharts-line-curve[name=\"SolarCells\"]'),\n    ).toBeVisible()\n    await expect(\n      page\n        .frameLocator('iframe[title=\"storybook-preview-iframe\"]')\n        .locator('path.recharts-curve.recharts-line-curve[name=\"Glass\"]'),\n    ).toBeVisible()\n  })\n})\n",
      "path": "src/components/SparkChart/sparkchart.spec.ts"
    }
  ]
}
