{
  "$schema": "https://ui.shadcn.com/schema/registry-item.json",
  "name": "icons-mistral",
  "type": "registry:component",
  "files": [
    {
      "type": "registry:component",
      "target": "components/icons/mistral.tsx",
      "content": "\n\nconst MistralAI = (props: React.SVGProps<SVGSVGElement>) => (\n    <svg\n        xmlns=\"http://www.w3.org/2000/svg\"\n        preserveAspectRatio=\"xMidYMid\"\n        viewBox=\"0 0 256 233\"\n        width=\"1em\"\n        height=\"1em\"\n        {...props}\n    >\n        <title>Mistral AI</title>\n        <path d=\"M186.18182 0h46.54545v46.54545h-46.54545z\" />\n        <path fill=\"#F7D046\" d=\"M209.45454 0h46.54545v46.54545h-46.54545z\" />\n        <path d=\"M0 0h46.54545v46.54545H0zM0 46.54545h46.54545V93.0909H0zM0 93.09091h46.54545v46.54545H0zM0 139.63636h46.54545v46.54545H0zM0 186.18182h46.54545v46.54545H0z\" />\n        <path fill=\"#F7D046\" d=\"M23.27273 0h46.54545v46.54545H23.27273z\" />\n        <path\n            fill=\"#F2A73B\"\n            d=\"M209.45454 46.54545h46.54545V93.0909h-46.54545zM23.27273 46.54545h46.54545V93.0909H23.27273z\"\n        />\n        <path d=\"M139.63636 46.54545h46.54545V93.0909h-46.54545z\" />\n        <path\n            fill=\"#F2A73B\"\n            d=\"M162.90909 46.54545h46.54545V93.0909h-46.54545zM69.81818 46.54545h46.54545V93.0909H69.81818z\"\n        />\n        <path\n            fill=\"#EE792F\"\n            d=\"M116.36364 93.09091h46.54545v46.54545h-46.54545zM162.90909 93.09091h46.54545v46.54545h-46.54545zM69.81818 93.09091h46.54545v46.54545H69.81818z\"\n        />\n        <path d=\"M93.09091 139.63636h46.54545v46.54545H93.09091z\" />\n        <path\n            fill=\"#EB5829\"\n            d=\"M116.36364 139.63636h46.54545v46.54545h-46.54545z\"\n        />\n        <path\n            fill=\"#EE792F\"\n            d=\"M209.45454 93.09091h46.54545v46.54545h-46.54545zM23.27273 93.09091h46.54545v46.54545H23.27273z\"\n        />\n        <path d=\"M186.18182 139.63636h46.54545v46.54545h-46.54545z\" />\n        <path\n            fill=\"#EB5829\"\n            d=\"M209.45454 139.63636h46.54545v46.54545h-46.54545z\"\n        />\n        <path d=\"M186.18182 186.18182h46.54545v46.54545h-46.54545z\" />\n        <path\n            fill=\"#EB5829\"\n            d=\"M23.27273 139.63636h46.54545v46.54545H23.27273z\"\n        />\n        <path\n            fill=\"#EA3326\"\n            d=\"M209.45454 186.18182h46.54545v46.54545h-46.54545zM23.27273 186.18182h46.54545v46.54545H23.27273z\"\n        />\n    </svg>\n);\nexport default MistralAI;\n",
      "path": "components/icons/mistral.tsx"
    }
  ]
}
