{
  "$schema": "https://ui.shadcn.com/schema/registry-item.json",
  "name": "Tabs/tabs.spec",
  "type": "registry:component",
  "dependencies": [
    "@playwright/test"
  ],
  "files": [
    {
      "type": "registry:component",
      "target": "components/Tabs/tabs.spec.tsx",
      "content": "import { expect, test } from \"@playwright/test\"\n\ntest.describe(\"Expect tabs variant-line\", () => {\n  test(\"to render tabs\", async ({ page }) => {\n    await page.goto(\"http://localhost:6006/?path=/story/ui-tabs--variant-line\")\n    await expect(\n      page\n        .frameLocator('iframe[title=\"storybook-preview-iframe\"]')\n        .getByText(\"ReturnsShipping\"),\n    ).toBeVisible()\n  })\n\n  test(\"to render a selected tab\", async ({ page }) => {\n    await page.goto(\"http://localhost:6006/?path=/story/ui-tabs--variant-line\")\n    await page\n      .frameLocator('iframe[title=\"storybook-preview-iframe\"]')\n      .getByRole(\"tab\", { name: \"Returns\" })\n      .click()\n    await expect(\n      page\n        .frameLocator('iframe[title=\"storybook-preview-iframe\"]')\n        .getByRole(\"tab\", { name: \"Returns\" }),\n    ).toHaveAttribute(\"aria-selected\", \"true\")\n    await expect(\n      page\n        .frameLocator('iframe[title=\"storybook-preview-iframe\"]')\n        .getByRole(\"tab\", { name: \"Shipping\" }),\n    ).toHaveAttribute(\"aria-selected\", \"false\")\n  })\n\n  test(\"to render a selected tab with content\", async ({ page }) => {\n    await page.goto(\"http://localhost:6006/?path=/story/ui-tabs--variant-line\")\n    await page\n      .frameLocator('iframe[title=\"storybook-preview-iframe\"]')\n      .getByRole(\"tab\", { name: \"Shipping\" })\n      .click()\n    await expect(\n      page\n        .frameLocator('iframe[title=\"storybook-preview-iframe\"]')\n        .getByRole(\"tab\", { name: \"Shipping\" }),\n    ).toHaveAttribute(\"aria-selected\", \"true\")\n    await expect(\n      page\n        .frameLocator('iframe[title=\"storybook-preview-iframe\"]')\n        .getByLabel(\"Shipping\"),\n    ).toContainText(\n      \"We ship worldwide via UPS Expedited. We offer flat rate shipping to customers in Canada ($30), the EU, Japan, and Singapore ($45–$65+), and Australia ($65). Note that most brokerage fees are included in the price of UPS Expedited shipping, with the exception of a possible $10 fee assessed in Canada only if prior arrangements to pay for duties and taxes are not made (see next question and answer).\",\n    )\n  })\n})\n\ntest.describe(\"Expect tabs disabled\", () => {\n  test(\"to render a disabled tab line\", async ({ page }) => {\n    await page.goto(\n      \"http://localhost:6006/?path=/story/ui-tabs--variant-line-disabled\",\n    )\n    await expect(\n      page\n        .frameLocator('iframe[title=\"storybook-preview-iframe\"]')\n        .getByRole(\"tab\", { name: \"Tab 3\" }),\n    ).toBeDisabled()\n  })\n  test(\"to render a disabled tab solid\", async ({ page }) => {\n    await page.goto(\n      \"http://localhost:6006/?path=/story/ui-tabs--variant-solid-disabled\",\n    )\n    await expect(\n      page\n        .frameLocator('iframe[title=\"storybook-preview-iframe\"]')\n        .getByRole(\"tab\", { name: \"Tab 3\" }),\n    ).toBeDisabled()\n  })\n})\n\ntest.describe(\"Expect tabs variant-solid\", () => {\n  test(\"to render tabs\", async ({ page }) => {\n    await page.goto(\"http://localhost:6006/?path=/story/ui-tabs--variant-solid\")\n    await expect(\n      page\n        .frameLocator('iframe[title=\"storybook-preview-iframe\"]')\n        .getByText(\"ReturnsShipping\"),\n    ).toBeVisible()\n  })\n\n  test(\"to render a selected tab\", async ({ page }) => {\n    await page.goto(\"http://localhost:6006/?path=/story/ui-tabs--variant-solid\")\n    await page\n      .frameLocator('iframe[title=\"storybook-preview-iframe\"]')\n      .getByRole(\"tab\", { name: \"Returns\" })\n      .click()\n    await expect(\n      page\n        .frameLocator('iframe[title=\"storybook-preview-iframe\"]')\n        .getByRole(\"tab\", { name: \"Returns\" }),\n    ).toHaveAttribute(\"aria-selected\", \"true\")\n    await expect(\n      page\n        .frameLocator('iframe[title=\"storybook-preview-iframe\"]')\n        .getByRole(\"tab\", { name: \"Shipping\" }),\n    ).toHaveAttribute(\"aria-selected\", \"false\")\n  })\n\n  test(\"to render a selected tab with content\", async ({ page }) => {\n    await page.goto(\"http://localhost:6006/?path=/story/ui-tabs--variant-solid\")\n    await page\n      .frameLocator('iframe[title=\"storybook-preview-iframe\"]')\n      .getByRole(\"tab\", { name: \"Shipping\" })\n      .click()\n    await expect(\n      page\n        .frameLocator('iframe[title=\"storybook-preview-iframe\"]')\n        .getByRole(\"tab\", { name: \"Shipping\" }),\n    ).toHaveAttribute(\"aria-selected\", \"true\")\n    await expect(\n      page\n        .frameLocator('iframe[title=\"storybook-preview-iframe\"]')\n        .getByLabel(\"Shipping\"),\n    ).toContainText(\n      \"We ship worldwide via UPS Expedited. We offer flat rate shipping to customers in Canada ($30), the EU, Japan, and Singapore ($45–$65+), and Australia ($65). Note that most brokerage fees are included in the price of UPS Expedited shipping, with the exception of a possible $10 fee assessed in Canada only if prior arrangements to pay for duties and taxes are not made (see next question and answer).\",\n    )\n  })\n})\n",
      "path": "src/components/Tabs/tabs.spec.tsx"
    }
  ]
}
